setup.py
ssh_config_gen/__init__.py
ssh_config_gen/gen.py
ssh_config_gen/main.py
ssh_config_gen.egg-info/PKG-INFO
ssh_config_gen.egg-info/SOURCES.txt
ssh_config_gen.egg-info/dependency_links.txt
ssh_config_gen.egg-info/entry_points.txt
ssh_config_gen.egg-info/requires.txt
ssh_config_gen.egg-info/top_level.txt