Metadata-Version: 1.0
Name: ssh-config-gen
Version: 0.1
Summary: Thing to generate an ssh config from
Home-page: UNKNOWN
Author: Stephen Moore
Author-email: stephen@delfick.com
License: WTFPL
Platform: UNKNOWN
